COPYING
README-py.md
README.md
compile.py
pyproject.toml
setup.py
hub-ctrl/hub-ctrl.c
klipper_klippy_l.egg-info/PKG-INFO
klipper_klippy_l.egg-info/SOURCES.txt
klipper_klippy_l.egg-info/dependency_links.txt
klipper_klippy_l.egg-info/entry_points.txt
klipper_klippy_l.egg-info/requires.txt
klipper_klippy_l.egg-info/top_level.txt
klippy/clocksync.py
klippy/configfile.py
klippy/console.py
klippy/gcode.py
klippy/klippy.py
klippy/mathutil.py
klippy/mcu.py
klippy/msgproto.py
klippy/parsedump.py
klippy/pins.py
klippy/queuelogger.py
klippy/reactor.py
klippy/serialhdl.py
klippy/stepper.py
klippy/toolhead.py
klippy/util.py
klippy/webhooks.py
klippy/chelper/__init__.py
klippy/chelper/builder.py
klippy/chelper/compiler.h
klippy/chelper/itersolve.c
klippy/chelper/itersolve.h
klippy/chelper/kin_cartesian.c
klippy/chelper/kin_corexy.c
klippy/chelper/kin_corexz.c
klippy/chelper/kin_delta.c
klippy/chelper/kin_deltesian.c
klippy/chelper/kin_extruder.c
klippy/chelper/kin_idex.c
klippy/chelper/kin_polar.c
klippy/chelper/kin_rotary_delta.c
klippy/chelper/kin_shaper.c
klippy/chelper/kin_winch.c
klippy/chelper/list.h
klippy/chelper/msgblock.c
klippy/chelper/msgblock.h
klippy/chelper/pollreactor.c
klippy/chelper/pollreactor.h
klippy/chelper/pyhelper.c
klippy/chelper/pyhelper.h
klippy/chelper/serialqueue.c
klippy/chelper/serialqueue.h
klippy/chelper/stepcompress.c
klippy/chelper/stepcompress.h
klippy/chelper/stock_pkginit.py
klippy/chelper/trapq.c
klippy/chelper/trapq.h
klippy/chelper/trdispatch.c
klippy/config/example-cartesian.cfg
klippy/config/example-corexy.cfg
klippy/config/example-corexz.cfg
klippy/config/example-delta.cfg
klippy/config/example-deltesian.cfg
klippy/config/example-extras.cfg
klippy/config/example-hybrid-corexy.cfg
klippy/config/example-hybrid-corexz.cfg
klippy/config/example-polar.cfg
klippy/config/example-rotary-delta.cfg
klippy/config/example-winch.cfg
klippy/config/example.cfg
klippy/config/generic-alligator-r2.cfg
klippy/config/generic-alligator-r3.cfg
klippy/config/generic-archim2.cfg
klippy/config/generic-azteeg-x5-mini-v3.cfg
klippy/config/generic-bigtreetech-e3-rrf-v1.1.cfg
klippy/config/generic-bigtreetech-gtr.cfg
klippy/config/generic-bigtreetech-manta-e3ez.cfg
