Metadata-Version: 2.1
Name: klipper-klippy-l
Version: 0.12.0.dev283
Summary: Klipper's host daemon - Unofficial repackage, includes patches
License: GPL-3.0-only
Project-URL: homepage, https://github.com/laikulo/klippy
License-File: COPYING
Requires-Dist: cffi==1.15.1
Requires-Dist: pyserial==3.4
Requires-Dist: greenlet==2.0.2
Requires-Dist: Jinja2==2.11.3
Requires-Dist: python-can==3.3.4
Requires-Dist: markupsafe==1.1.1
Provides-Extra: resonancetest
Requires-Dist: numpy; extra == "resonancetest"
Requires-Dist: matplotlib; extra == "resonancetest"
